pdf_shuffle/__init__.py
pdf_shuffle/__main__.py
pdf_shuffle/static/index.css
pdf_shuffle/static/index.js
pdf_shuffle/templates/index.html
pdf_shuffle/util.py
pdf_shuffle/views.py
pdf_shuffle-0.2.1.dist-info/entry_points.txt
pdf_shuffle-0.2.1.dist-info/LICENSE
pdf_shuffle-0.2.1.dist-info/WHEEL
pdf_shuffle-0.2.1.dist-info/METADATA
pdf_shuffle-0.2.1.dist-info/RECORD
