Metadata-Version: 2.1
Name: pdf-shuffle
Version: 0.2.1
Summary: A PDF page/image randomizer, or flashcard quiz from a PDF.
Home-page: https://github.com/patarapolw/pdf-shuffle
License: MIT
Keywords: pdf,flashcard
Author: patarapolw
Author-email: patarapolw@gmail.com
Classifier: License :: OSI Approved :: MIT License
Classifier: Programming Language :: Python :: 2
Classifier: Programming Language :: Python :: 2.7
Classifier: Programming Language :: Python :: 3
Classifier: Programming Language :: Python :: 3.4
Classifier: Programming Language :: Python :: 3.5
Classifier: Programming Language :: Python :: 3.6
Classifier: Programming Language :: Python :: 3.7
Requires-Dist: click (>=7.0,<8.0)
Requires-Dist: flask (>=1.0,<2.0)
